{"InvoiceNo":562046,"StockCode":"22747","Quantity":6,"UnitPrice":"2.1","CustomerID":12378.0}
{"InvoiceNo":562046,"StockCode":"85227","Quantity":12,"UnitPrice":"0.85","CustomerID":12378.0}
{"InvoiceNo":562046,"StockCode":"22746","Quantity":6,"UnitPrice":"2.1","CustomerID":12378.0}
{"InvoiceNo":562046,"StockCode":"22748","Quantity":6,"UnitPrice":"2.1","CustomerID":12378.0}
{"InvoiceNo":562046,"StockCode":"22550","Quantity":4,"UnitPrice":"3.75","CustomerID":12378.0}
{"InvoiceNo":562046,"StockCode":"22619","Quantity":8,"UnitPrice":"3.75","CustomerID":12378.0}
{"InvoiceNo":562046,"StockCode":"23229","Quantity":6,"UnitPrice":"3.75","CustomerID":12378.0}
{"InvoiceNo":562046,"StockCode":"23080","Quantity":2,"UnitPrice":"8.25","CustomerID":12378.0}
{"InvoiceNo":562046,"StockCode":"84568","Quantity":288,"UnitPrice":"0.21","CustomerID":12378.0}
{"InvoiceNo":562046,"StockCode":"22332","Quantity":8,"UnitPrice":"1.65","CustomerID":12378.0}
{"InvoiceNo":562046,"StockCode":"47599A","Quantity":6,"UnitPrice":"2.1","CustomerID":12378.0}
{"InvoiceNo":562046,"StockCode":"22333","Quantity":16,"UnitPrice":"1.65","CustomerID":12378.0}
{"InvoiceNo":562046,"StockCode":"22334","Quantity":8,"UnitPrice":"1.65","CustomerID":12378.0}
{"InvoiceNo":562046,"StockCode":"21935","Quantity":10,"UnitPrice":"1.65","CustomerID":12378.0}
{"InvoiceNo":562046,"StockCode":"22374","Quantity":4,"UnitPrice":"4.25","CustomerID":12378.0}
{"InvoiceNo":562046,"StockCode":"22371","Quantity":4,"UnitPrice":"4.25","CustomerID":12378.0}
{"InvoiceNo":562046,"StockCode":"21039","Quantity":12,"UnitPrice":"2.55","CustomerID":12378.0}
{"InvoiceNo":562046,"StockCode":"23000","Quantity":24,"UnitPrice":"0.42","CustomerID":12378.0}
{"InvoiceNo":562046,"StockCode":"20750","Quantity":4,"UnitPrice":"7.95","CustomerID":12378.0}
{"InvoiceNo":562046,"StockCode":"20682","Quantity":6,"UnitPrice":"3.25","CustomerID":12378.0}
{"InvoiceNo":562046,"StockCode":"20686","Quantity":6,"UnitPrice":"3.25","CustomerID":12378.0}
{"InvoiceNo":562046,"StockCode":"21707","Quantity":4,"UnitPrice":"4.95","CustomerID":12378.0}
{"InvoiceNo":562046,"StockCode":"21709","Quantity":4,"UnitPrice":"4.95","CustomerID":12378.0}
{"InvoiceNo":562046,"StockCode":"21706","Quantity":4,"UnitPrice":"4.95","CustomerID":12378.0}
{"InvoiceNo":562046,"StockCode":"85014A","Quantity":3,"UnitPrice":"5.95","CustomerID":12378.0}
{"InvoiceNo":562046,"StockCode":"22449","Quantity":6,"UnitPrice":"3.35","CustomerID":12378.0}
{"InvoiceNo":562046,"StockCode":"84912A","Quantity":4,"UnitPrice":"3.75","CustomerID":12378.0}
{"InvoiceNo":562046,"StockCode":"22687","Quantity":2,"UnitPrice":"7.95","CustomerID":12378.0}
{"InvoiceNo":562046,"StockCode":"22737","Quantity":10,"UnitPrice":"1.65","CustomerID":12378.0}
{"InvoiceNo":562046,"StockCode":"22739","Quantity":10,"UnitPrice":"1.65","CustomerID":12378.0}
{"InvoiceNo":562046,"StockCode":"22075","Quantity":12,"UnitPrice":"1.65","CustomerID":12378.0}
{"InvoiceNo":562046,"StockCode":"23319","Quantity":12,"UnitPrice":"2.49","CustomerID":12378.0}
{"InvoiceNo":562046,"StockCode":"22589","Quantity":6,"UnitPrice":"2.55","CustomerID":12378.0}
{"InvoiceNo":562046,"StockCode":"23267","Quantity":12,"UnitPrice":"1.25","CustomerID":12378.0}
{"InvoiceNo":562046,"StockCode":"23101","Quantity":12,"UnitPrice":"0.83","CustomerID":12378.0}
{"InvoiceNo":562046,"StockCode":"23102","Quantity":12,"UnitPrice":"0.83","CustomerID":12378.0}
{"InvoiceNo":562046,"StockCode":"23129","Quantity":4,"UnitPrice":"4.15","CustomerID":12378.0}
{"InvoiceNo":562046,"StockCode":"23223","Quantity":12,"UnitPrice":"0.83","CustomerID":12378.0}
{"InvoiceNo":562046,"StockCode":"23221","Quantity":12,"UnitPrice":"0.83","CustomerID":12378.0}
{"InvoiceNo":562046,"StockCode":"22945","Quantity":12,"UnitPrice":"0.85","CustomerID":12378.0}
{"InvoiceNo":562046,"StockCode":"21098","Quantity":24,"UnitPrice":"1.25","CustomerID":12378.0}
{"InvoiceNo":562046,"StockCode":"23311","Quantity":12,"UnitPrice":"2.55","CustomerID":12378.0}
{"InvoiceNo":562046,"StockCode":"23268","Quantity":12,"UnitPrice":"1.45","CustomerID":12378.0}
{"InvoiceNo":562046,"StockCode":"23270","Quantity":12,"UnitPrice":"1.45","CustomerID":12378.0}
{"InvoiceNo":562046,"StockCode":"22942","Quantity":2,"UnitPrice":"8.5","CustomerID":12378.0}
{"InvoiceNo":562046,"StockCode":"22943","Quantity":3,"UnitPrice":"4.95","CustomerID":12378.0}
{"InvoiceNo":562046,"StockCode":"85048","Quantity":2,"UnitPrice":"7.95","CustomerID":12378.0}
{"InvoiceNo":562046,"StockCode":"22957","Quantity":6,"UnitPrice":"2.95","CustomerID":12378.0}
{"InvoiceNo":562046,"StockCode":"22857","Quantity":12,"UnitPrice":"0.85","CustomerID":12378.0}
{"InvoiceNo":562046,"StockCode":"22148","Quantity":12,"UnitPrice":"1.95","CustomerID":12378.0}
{"InvoiceNo":562046,"StockCode":"22254","Quantity":12,"UnitPrice":"1.25","CustomerID":12378.0}
{"InvoiceNo":562046,"StockCode":"22255","Quantity":12,"UnitPrice":"0.85","CustomerID":12378.0}
{"InvoiceNo":562046,"StockCode":"22729","Quantity":4,"UnitPrice":"3.75","CustomerID":12378.0}
{"InvoiceNo":562046,"StockCode":"22189","Quantity":4,"UnitPrice":"3.95","CustomerID":12378.0}
{"InvoiceNo":562046,"StockCode":"22588","Quantity":6,"UnitPrice":"2.89","CustomerID":12378.0}
{"InvoiceNo":562046,"StockCode":"22435","Quantity":12,"UnitPrice":"1.25","CustomerID":12378.0}
{"InvoiceNo":562046,"StockCode":"22434","Quantity":8,"UnitPrice":"1.95","CustomerID":12378.0}
{"InvoiceNo":562046,"StockCode":"22436","Quantity":20,"UnitPrice":"0.65","CustomerID":12378.0}
{"InvoiceNo":562046,"StockCode":"22930","Quantity":6,"UnitPrice":"2.55","CustomerID":12378.0}
{"InvoiceNo":562046,"StockCode":"47559B","Quantity":10,"UnitPrice":"1.25","CustomerID":12378.0}
{"InvoiceNo":562046,"StockCode":"21154","Quantity":10,"UnitPrice":"1.25","CustomerID":12378.0}
{"InvoiceNo":562046,"StockCode":"21212","Quantity":24,"UnitPrice":"0.55","CustomerID":12378.0}
{"InvoiceNo":562046,"StockCode":"20754","Quantity":6,"UnitPrice":"2.1","CustomerID":12378.0}
{"InvoiceNo":562046,"StockCode":"22852","Quantity":4,"UnitPrice":"4.25","CustomerID":12378.0}
{"InvoiceNo":562046,"StockCode":"23183","Quantity":6,"UnitPrice":"3.75","CustomerID":12378.0}
{"InvoiceNo":562046,"StockCode":"22981","Quantity":12,"UnitPrice":"1.45","CustomerID":12378.0}
{"InvoiceNo":562046,"StockCode":"22982","Quantity":12,"UnitPrice":"1.25","CustomerID":12378.0}
{"InvoiceNo":562046,"StockCode":"84828","Quantity":12,"UnitPrice":"1.25","CustomerID":12378.0}
{"InvoiceNo":562046,"StockCode":"84378","Quantity":12,"UnitPrice":"1.25","CustomerID":12378.0}
{"InvoiceNo":562046,"StockCode":"22965","Quantity":6,"UnitPrice":"2.1","CustomerID":12378.0}
{"InvoiceNo":562046,"StockCode":"84380","Quantity":12,"UnitPrice":"1.25","CustomerID":12378.0}
{"InvoiceNo":562046,"StockCode":"22966","Quantity":12,"UnitPrice":"1.25","CustomerID":12378.0}
{"InvoiceNo":562046,"StockCode":"22964","Quantity":6,"UnitPrice":"2.1","CustomerID":12378.0}
{"InvoiceNo":562046,"StockCode":"20725","Quantity":20,"UnitPrice":"1.65","CustomerID":12378.0}
{"InvoiceNo":562046,"StockCode":"20728","Quantity":10,"UnitPrice":"1.65","CustomerID":12378.0}
{"InvoiceNo":562046,"StockCode":"21561","Quantity":6,"UnitPrice":"2.55","CustomerID":12378.0}
{"InvoiceNo":562046,"StockCode":"21558","Quantity":6,"UnitPrice":"2.55","CustomerID":12378.0}
{"InvoiceNo":562046,"StockCode":"22326","Quantity":12,"UnitPrice":"2.95","CustomerID":12378.0}
{"InvoiceNo":562046,"StockCode":"21559","Quantity":6,"UnitPrice":"2.55","CustomerID":12378.0}
{"InvoiceNo":562046,"StockCode":"22328","Quantity":6,"UnitPrice":"2.95","CustomerID":12378.0}
{"InvoiceNo":562046,"StockCode":"22628","Quantity":4,"UnitPrice":"4.95","CustomerID":12378.0}
{"InvoiceNo":562046,"StockCode":"22329","Quantity":12,"UnitPrice":"1.65","CustomerID":12378.0}
{"InvoiceNo":562046,"StockCode":"22629","Quantity":12,"UnitPrice":"1.95","CustomerID":12378.0}
{"InvoiceNo":562046,"StockCode":"22383","Quantity":10,"UnitPrice":"1.65","CustomerID":12378.0}
{"InvoiceNo":562046,"StockCode":"22384","Quantity":10,"UnitPrice":"1.65","CustomerID":12378.0}
{"InvoiceNo":562046,"StockCode":"22631","Quantity":12,"UnitPrice":"1.95","CustomerID":12378.0}
{"InvoiceNo":562046,"StockCode":"23206","Quantity":10,"UnitPrice":"1.65","CustomerID":12378.0}
{"InvoiceNo":562046,"StockCode":"22659","Quantity":12,"UnitPrice":"1.95","CustomerID":12378.0}
{"InvoiceNo":562046,"StockCode":"23207","Quantity":10,"UnitPrice":"1.65","CustomerID":12378.0}
{"InvoiceNo":562046,"StockCode":"23209","Quantity":10,"UnitPrice":"1.65","CustomerID":12378.0}
{"InvoiceNo":562046,"StockCode":"22990","Quantity":2,"UnitPrice":"4.95","CustomerID":12378.0}
{"InvoiceNo":562046,"StockCode":"47567B","Quantity":3,"UnitPrice":"5.95","CustomerID":12378.0}
{"InvoiceNo":562046,"StockCode":"47591D","Quantity":16,"UnitPrice":"1.95","CustomerID":12378.0}
{"InvoiceNo":562046,"StockCode":"23252","Quantity":4,"UnitPrice":"3.75","CustomerID":12378.0}
{"InvoiceNo":562046,"StockCode":"23251","Quantity":12,"UnitPrice":"1.25","CustomerID":12378.0}
{"InvoiceNo":562046,"StockCode":"23250","Quantity":12,"UnitPrice":"1.25","CustomerID":12378.0}
{"InvoiceNo":562046,"StockCode":"23249","Quantity":12,"UnitPrice":"1.65","CustomerID":12378.0}
{"InvoiceNo":562046,"StockCode":"22839","Quantity":1,"UnitPrice":"14.95","CustomerID":12378.0}
{"InvoiceNo":562046,"StockCode":"22838","Quantity":1,"UnitPrice":"14.95","CustomerID":12378.0}
{"InvoiceNo":562046,"StockCode":"22841","Quantity":2,"UnitPrice":"7.95","CustomerID":12378.0}
{"InvoiceNo":562046,"StockCode":"22840","Quantity":2,"UnitPrice":"7.95","CustomerID":12378.0}
{"InvoiceNo":562046,"StockCode":"22846","Quantity":1,"UnitPrice":"16.95","CustomerID":12378.0}
{"InvoiceNo":562046,"StockCode":"21086","Quantity":48,"UnitPrice":"0.65","CustomerID":12378.0}
{"InvoiceNo":562046,"StockCode":"21936","Quantity":5,"UnitPrice":"2.95","CustomerID":12378.0}
{"InvoiceNo":562046,"StockCode":"21094","Quantity":48,"UnitPrice":"0.85","CustomerID":12378.0}
{"InvoiceNo":562046,"StockCode":"21988","Quantity":12,"UnitPrice":"0.85","CustomerID":12378.0}
{"InvoiceNo":562046,"StockCode":"21987","Quantity":12,"UnitPrice":"0.65","CustomerID":12378.0}
{"InvoiceNo":562046,"StockCode":"21080","Quantity":48,"UnitPrice":"0.85","CustomerID":12378.0}
{"InvoiceNo":562046,"StockCode":"22851","Quantity":12,"UnitPrice":"0.85","CustomerID":12378.0}
{"InvoiceNo":562046,"StockCode":"22907","Quantity":12,"UnitPrice":"0.85","CustomerID":12378.0}
{"InvoiceNo":562046,"StockCode":"21078","Quantity":12,"UnitPrice":"0.85","CustomerID":12378.0}
{"InvoiceNo":562046,"StockCode":"21989","Quantity":24,"UnitPrice":"0.85","CustomerID":12378.0}
{"InvoiceNo":562046,"StockCode":"23253","Quantity":2,"UnitPrice":"15.95","CustomerID":12378.0}
{"InvoiceNo":562046,"StockCode":"23119","Quantity":12,"UnitPrice":"0.62","CustomerID":12378.0}
{"InvoiceNo":562046,"StockCode":"21242","Quantity":24,"UnitPrice":"1.69","CustomerID":12378.0}
{"InvoiceNo":562046,"StockCode":"21244","Quantity":16,"UnitPrice":"1.69","CustomerID":12378.0}
{"InvoiceNo":562046,"StockCode":"21245","Quantity":8,"UnitPrice":"1.69","CustomerID":12378.0}
{"InvoiceNo":562046,"StockCode":"21243","Quantity":16,"UnitPrice":"1.69","CustomerID":12378.0}
{"InvoiceNo":562046,"StockCode":"21238","Quantity":24,"UnitPrice":"0.85","CustomerID":12378.0}
{"InvoiceNo":562046,"StockCode":"23285","Quantity":24,"UnitPrice":"0.85","CustomerID":12378.0}
{"InvoiceNo":562046,"StockCode":"23286","Quantity":24,"UnitPrice":"0.85","CustomerID":12378.0}
{"InvoiceNo":562046,"StockCode":"23287","Quantity":24,"UnitPrice":"0.85","CustomerID":12378.0}
{"InvoiceNo":562046,"StockCode":"21240","Quantity":8,"UnitPrice":"0.85","CustomerID":12378.0}
{"InvoiceNo":562046,"StockCode":"21239","Quantity":8,"UnitPrice":"0.85","CustomerID":12378.0}
{"InvoiceNo":562046,"StockCode":"23288","Quantity":16,"UnitPrice":"0.85","CustomerID":12378.0}
{"InvoiceNo":562046,"StockCode":"23346","Quantity":12,"UnitPrice":"1.25","CustomerID":12378.0}
{"InvoiceNo":562046,"StockCode":"23347","Quantity":12,"UnitPrice":"1.25","CustomerID":12378.0}
{"InvoiceNo":562046,"StockCode":"20674","Quantity":8,"UnitPrice":"1.25","CustomerID":12378.0}
{"InvoiceNo":562046,"StockCode":"20675","Quantity":8,"UnitPrice":"1.25","CustomerID":12378.0}
{"InvoiceNo":562046,"StockCode":"20677","Quantity":16,"UnitPrice":"1.25","CustomerID":12378.0}
{"InvoiceNo":562046,"StockCode":"20676","Quantity":24,"UnitPrice":"1.25","CustomerID":12378.0}
{"InvoiceNo":562046,"StockCode":"21537","Quantity":4,"UnitPrice":"4.25","CustomerID":12378.0}
{"InvoiceNo":562046,"StockCode":"84988","Quantity":12,"UnitPrice":"1.45","CustomerID":12378.0}
{"InvoiceNo":562046,"StockCode":"84987","Quantity":12,"UnitPrice":"1.45","CustomerID":12378.0}
{"InvoiceNo":562046,"StockCode":"21844","Quantity":12,"UnitPrice":"2.95","CustomerID":12378.0}
{"InvoiceNo":562046,"StockCode":"84997D","Quantity":4,"UnitPrice":"4.15","CustomerID":12378.0}
{"InvoiceNo":562046,"StockCode":"84997B","Quantity":4,"UnitPrice":"4.15","CustomerID":12378.0}
{"InvoiceNo":562046,"StockCode":"23256","Quantity":4,"UnitPrice":"4.15","CustomerID":12378.0}
{"InvoiceNo":562046,"StockCode":"23255","Quantity":4,"UnitPrice":"4.15","CustomerID":12378.0}
{"InvoiceNo":562046,"StockCode":"23254","Quantity":4,"UnitPrice":"4.15","CustomerID":12378.0}
{"InvoiceNo":562046,"StockCode":"22820","Quantity":12,"UnitPrice":"0.65","CustomerID":12378.0}
{"InvoiceNo":562046,"StockCode":"22583","Quantity":6,"UnitPrice":"2.55","CustomerID":12378.0}
{"InvoiceNo":562046,"StockCode":"22584","Quantity":6,"UnitPrice":"2.55","CustomerID":12378.0}
{"InvoiceNo":562046,"StockCode":"21288","Quantity":6,"UnitPrice":"2.95","CustomerID":12378.0}
{"InvoiceNo":562046,"StockCode":"22585","Quantity":12,"UnitPrice":"1.25","CustomerID":12378.0}
{"InvoiceNo":562046,"StockCode":"23231","Quantity":25,"UnitPrice":"0.42","CustomerID":12378.0}
{"InvoiceNo":562046,"StockCode":"23550","Quantity":25,"UnitPrice":"0.42","CustomerID":12378.0}
{"InvoiceNo":562046,"StockCode":"16161U","Quantity":25,"UnitPrice":"0.42","CustomerID":12378.0}
{"InvoiceNo":562046,"StockCode":"22605","Quantity":1,"UnitPrice":"14.95","CustomerID":12378.0}
{"InvoiceNo":562046,"StockCode":"22365","Quantity":2,"UnitPrice":"7.95","CustomerID":12378.0}
{"InvoiceNo":562046,"StockCode":"20685","Quantity":2,"UnitPrice":"7.95","CustomerID":12378.0}
{"InvoiceNo":562046,"StockCode":"22692","Quantity":4,"UnitPrice":"7.95","CustomerID":12378.0}
{"InvoiceNo":562046,"StockCode":"48138","Quantity":2,"UnitPrice":"7.95","CustomerID":12378.0}
{"InvoiceNo":562046,"StockCode":"22822","Quantity":4,"UnitPrice":"5.95","CustomerID":12378.0}
{"InvoiceNo":562046,"StockCode":"22478","Quantity":10,"UnitPrice":"1.25","CustomerID":12378.0}
{"InvoiceNo":562046,"StockCode":"15058B","Quantity":2,"UnitPrice":"7.95","CustomerID":12378.0}
{"InvoiceNo":562046,"StockCode":"22430","Quantity":4,"UnitPrice":"4.95","CustomerID":12378.0}
{"InvoiceNo":562046,"StockCode":"22431","Quantity":6,"UnitPrice":"1.95","CustomerID":12378.0}
{"InvoiceNo":562046,"StockCode":"22432","Quantity":6,"UnitPrice":"1.95","CustomerID":12378.0}
{"InvoiceNo":562046,"StockCode":"22693","Quantity":24,"UnitPrice":"1.25","CustomerID":12378.0}
{"InvoiceNo":562046,"StockCode":"22742","Quantity":6,"UnitPrice":"2.95","CustomerID":12378.0}
{"InvoiceNo":562046,"StockCode":"22743","Quantity":6,"UnitPrice":"2.95","CustomerID":12378.0}
{"InvoiceNo":562046,"StockCode":"22074","Quantity":12,"UnitPrice":"1.65","CustomerID":12378.0}
{"InvoiceNo":562046,"StockCode":"85049G","Quantity":12,"UnitPrice":"1.25","CustomerID":12378.0}
{"InvoiceNo":562046,"StockCode":"22452","Quantity":6,"UnitPrice":"2.95","CustomerID":12378.0}
{"InvoiceNo":562046,"StockCode":"22271","Quantity":6,"UnitPrice":"2.95","CustomerID":12378.0}
{"InvoiceNo":562046,"StockCode":"22273","Quantity":6,"UnitPrice":"2.95","CustomerID":12378.0}
{"InvoiceNo":562046,"StockCode":"22669","Quantity":5,"UnitPrice":"2.95","CustomerID":12378.0}
{"InvoiceNo":562046,"StockCode":"47590A","Quantity":3,"UnitPrice":"5.45","CustomerID":12378.0}
{"InvoiceNo":562046,"StockCode":"47590B","Quantity":3,"UnitPrice":"5.45","CustomerID":12378.0}
{"InvoiceNo":562046,"StockCode":"23298","Quantity":6,"UnitPrice":"4.95","CustomerID":12378.0}
{"InvoiceNo":562046,"StockCode":"21668","Quantity":12,"UnitPrice":"1.25","CustomerID":12378.0}
{"InvoiceNo":562046,"StockCode":"21671","Quantity":12,"UnitPrice":"1.25","CustomerID":12378.0}
{"InvoiceNo":562046,"StockCode":"21672","Quantity":12,"UnitPrice":"1.25","CustomerID":12378.0}
{"InvoiceNo":562046,"StockCode":"22770","Quantity":2,"UnitPrice":"14.95","CustomerID":12378.0}
{"InvoiceNo":562046,"StockCode":"22325","Quantity":9,"UnitPrice":"4.95","CustomerID":12378.0}
{"InvoiceNo":562046,"StockCode":"22318","Quantity":6,"UnitPrice":"2.95","CustomerID":12378.0}
{"InvoiceNo":562046,"StockCode":"22320","Quantity":9,"UnitPrice":"5.95","CustomerID":12378.0}
{"InvoiceNo":562046,"StockCode":"21114","Quantity":10,"UnitPrice":"1.25","CustomerID":12378.0}
{"InvoiceNo":562046,"StockCode":"22602","Quantity":12,"UnitPrice":"0.85","CustomerID":12378.0}
{"InvoiceNo":562046,"StockCode":"21208","Quantity":12,"UnitPrice":"0.39","CustomerID":12378.0}
{"InvoiceNo":562046,"StockCode":"22670","Quantity":12,"UnitPrice":"1.25","CustomerID":12378.0}
{"InvoiceNo":562046,"StockCode":"82551","Quantity":12,"UnitPrice":"1.45","CustomerID":12378.0}
{"InvoiceNo":562046,"StockCode":"22728","Quantity":4,"UnitPrice":"3.75","CustomerID":12378.0}
{"InvoiceNo":562046,"StockCode":"22726","Quantity":4,"UnitPrice":"3.75","CustomerID":12378.0}
{"InvoiceNo":562046,"StockCode":"23316","Quantity":2,"UnitPrice":"9.95","CustomerID":12378.0}
{"InvoiceNo":562046,"StockCode":"23317","Quantity":2,"UnitPrice":"9.95","CustomerID":12378.0}
{"InvoiceNo":562046,"StockCode":"22914","Quantity":3,"UnitPrice":"4.95","CustomerID":12378.0}
{"InvoiceNo":562046,"StockCode":"23147","Quantity":12,"UnitPrice":"1.45","CustomerID":12378.0}
{"InvoiceNo":562046,"StockCode":"23148","Quantity":12,"UnitPrice":"0.83","CustomerID":12378.0}
{"InvoiceNo":562046,"StockCode":"84792","Quantity":4,"UnitPrice":"4.65","CustomerID":12378.0}
{"InvoiceNo":562046,"StockCode":"21201","Quantity":12,"UnitPrice":"2.55","CustomerID":12378.0}
{"InvoiceNo":562046,"StockCode":"21188","Quantity":12,"UnitPrice":"2.95","CustomerID":12378.0}
{"InvoiceNo":562046,"StockCode":"21205","Quantity":6,"UnitPrice":"2.55","CustomerID":12378.0}
{"InvoiceNo":562046,"StockCode":"23108","Quantity":6,"UnitPrice":"6.25","CustomerID":12378.0}
{"InvoiceNo":562046,"StockCode":"23109","Quantity":24,"UnitPrice":"2.89","CustomerID":12378.0}
{"InvoiceNo":562046,"StockCode":"22779","Quantity":4,"UnitPrice":"4.25","CustomerID":12378.0}
{"InvoiceNo":562046,"StockCode":"22615","Quantity":24,"UnitPrice":"0.29","CustomerID":12378.0}
{"InvoiceNo":562046,"StockCode":"21967","Quantity":24,"UnitPrice":"0.29","CustomerID":12378.0}
{"InvoiceNo":562046,"StockCode":"21985","Quantity":24,"UnitPrice":"0.29","CustomerID":12378.0}
{"InvoiceNo":562046,"StockCode":"21982","Quantity":24,"UnitPrice":"0.29","CustomerID":12378.0}
{"InvoiceNo":562046,"StockCode":"21981","Quantity":24,"UnitPrice":"0.29","CustomerID":12378.0}
{"InvoiceNo":562046,"StockCode":"22760","Quantity":4,"UnitPrice":"12.75","CustomerID":12378.0}
{"InvoiceNo":562046,"StockCode":"22313","Quantity":6,"UnitPrice":"2.95","CustomerID":12378.0}
{"InvoiceNo":562046,"StockCode":"22314","Quantity":6,"UnitPrice":"2.95","CustomerID":12378.0}
{"InvoiceNo":562046,"StockCode":"21731","Quantity":12,"UnitPrice":"1.65","CustomerID":12378.0}
{"InvoiceNo":562046,"StockCode":"23156","Quantity":12,"UnitPrice":"2.08","CustomerID":12378.0}
{"InvoiceNo":562046,"StockCode":"23155","Quantity":12,"UnitPrice":"0.83","CustomerID":12378.0}
{"InvoiceNo":562046,"StockCode":"23159","Quantity":12,"UnitPrice":"2.08","CustomerID":12378.0}
{"InvoiceNo":562046,"StockCode":"23157","Quantity":12,"UnitPrice":"2.08","CustomerID":12378.0}
{"InvoiceNo":562046,"StockCode":"21556","Quantity":6,"UnitPrice":"2.55","CustomerID":12378.0}
{"InvoiceNo":562046,"StockCode":"23176","Quantity":8,"UnitPrice":"2.25","CustomerID":12378.0}
{"InvoiceNo":562046,"StockCode":"23193","Quantity":8,"UnitPrice":"2.25","CustomerID":12378.0}
{"InvoiceNo":562046,"StockCode":"23194","Quantity":8,"UnitPrice":"2.25","CustomerID":12378.0}
{"InvoiceNo":562046,"StockCode":"23177","Quantity":8,"UnitPrice":"2.25","CustomerID":12378.0}
{"InvoiceNo":562046,"StockCode":"23077","Quantity":20,"UnitPrice":"1.25","CustomerID":12378.0}
{"InvoiceNo":562046,"StockCode":"22535","Quantity":24,"UnitPrice":"0.42","CustomerID":12378.0}
{"InvoiceNo":562046,"StockCode":"22532","Quantity":24,"UnitPrice":"0.42","CustomerID":12378.0}
{"InvoiceNo":562046,"StockCode":"22745","Quantity":6,"UnitPrice":"2.1","CustomerID":12378.0}
{"InvoiceNo":574740,"StockCode":"22064","Quantity":12,"UnitPrice":"1.65","CustomerID":12357.0}
{"InvoiceNo":574740,"StockCode":"21232","Quantity":12,"UnitPrice":"1.25","CustomerID":12357.0}
{"InvoiceNo":574740,"StockCode":"22066","Quantity":48,"UnitPrice":"0.39","CustomerID":12357.0}
{"InvoiceNo":574740,"StockCode":"22067","Quantity":12,"UnitPrice":"1.65","CustomerID":12357.0}
{"InvoiceNo":574740,"StockCode":"21555","Quantity":6,"UnitPrice":"2.55","CustomerID":12357.0}
{"InvoiceNo":574740,"StockCode":"22316","Quantity":12,"UnitPrice":"1.25","CustomerID":12357.0}
{"InvoiceNo":574740,"StockCode":"22315","Quantity":12,"UnitPrice":"1.25","CustomerID":12357.0}
{"InvoiceNo":574740,"StockCode":"21843","Quantity":6,"UnitPrice":"10.95","CustomerID":12357.0}
{"InvoiceNo":574740,"StockCode":"22061","Quantity":12,"UnitPrice":"8.5","CustomerID":12357.0}
{"InvoiceNo":574740,"StockCode":"22890","Quantity":12,"UnitPrice":"8.5","CustomerID":12357.0}
{"InvoiceNo":574740,"StockCode":"37449","Quantity":8,"UnitPrice":"8.5","CustomerID":12357.0}
{"InvoiceNo":574740,"StockCode":"22423","Quantity":8,"UnitPrice":"12.75","CustomerID":12357.0}
{"InvoiceNo":574740,"StockCode":"37446","Quantity":16,"UnitPrice":"1.45","CustomerID":12357.0}
{"InvoiceNo":574740,"StockCode":"22055","Quantity":16,"UnitPrice":"1.65","CustomerID":12357.0}
{"InvoiceNo":574740,"StockCode":"20676","Quantity":72,"UnitPrice":"1.06","CustomerID":12357.0}
{"InvoiceNo":574740,"StockCode":"20677","Quantity":16,"UnitPrice":"1.25","CustomerID":12357.0}
{"InvoiceNo":574740,"StockCode":"22072","Quantity":24,"UnitPrice":"3.39","CustomerID":12357.0}
{"InvoiceNo":574740,"StockCode":"22070","Quantity":36,"UnitPrice":"3.39","CustomerID":12357.0}
{"InvoiceNo":574740,"StockCode":"22071","Quantity":36,"UnitPrice":"3.39","CustomerID":12357.0}
{"InvoiceNo":574740,"StockCode":"22190","Quantity":12,"UnitPrice":"2.1","CustomerID":12357.0}
{"InvoiceNo":574740,"StockCode":"21844","Quantity":24,"UnitPrice":"2.95","CustomerID":12357.0}
{"InvoiceNo":574740,"StockCode":"21874","Quantity":12,"UnitPrice":"1.65","CustomerID":12357.0}
{"InvoiceNo":574740,"StockCode":"22059","Quantity":12,"UnitPrice":"1.49","CustomerID":12357.0}
{"InvoiceNo":574740,"StockCode":"37448","Quantity":12,"UnitPrice":"1.49","CustomerID":12357.0}
{"InvoiceNo":574740,"StockCode":"22632","Quantity":96,"UnitPrice":"1.85","CustomerID":12357.0}
{"InvoiceNo":574740,"StockCode":"22312","Quantity":24,"UnitPrice":"2.95","CustomerID":12357.0}
{"InvoiceNo":574740,"StockCode":"22903","Quantity":12,"UnitPrice":"2.95","CustomerID":12357.0}
{"InvoiceNo":574740,"StockCode":"22904","Quantity":12,"UnitPrice":"2.95","CustomerID":12357.0}
{"InvoiceNo":574740,"StockCode":"22905","Quantity":12,"UnitPrice":"2.95","CustomerID":12357.0}
{"InvoiceNo":574740,"StockCode":"22333","Quantity":24,"UnitPrice":"1.65","CustomerID":12357.0}
{"InvoiceNo":574740,"StockCode":"21039","Quantity":12,"UnitPrice":"2.55","CustomerID":12357.0}
{"InvoiceNo":574740,"StockCode":"20750","Quantity":12,"UnitPrice":"6.35","CustomerID":12357.0}
{"InvoiceNo":574740,"StockCode":"85014A","Quantity":12,"UnitPrice":"5.95","CustomerID":12357.0}
{"InvoiceNo":574740,"StockCode":"85014B","Quantity":48,"UnitPrice":"4.95","CustomerID":12357.0}
{"InvoiceNo":574740,"StockCode":"15056BL","Quantity":9,"UnitPrice":"5.95","CustomerID":12357.0}
{"InvoiceNo":574740,"StockCode":"15056P","Quantity":3,"UnitPrice":"5.95","CustomerID":12357.0}
{"InvoiceNo":574740,"StockCode":"20679","Quantity":9,"UnitPrice":"5.95","CustomerID":12357.0}
{"InvoiceNo":574740,"StockCode":"84665","Quantity":4,"UnitPrice":"5.95","CustomerID":12357.0}
{"InvoiceNo":574740,"StockCode":"21485","Quantity":24,"UnitPrice":"4.25","CustomerID":12357.0}
{"InvoiceNo":574740,"StockCode":"23357","Quantity":24,"UnitPrice":"4.15","CustomerID":12357.0}
{"InvoiceNo":574740,"StockCode":"84029G","Quantity":24,"UnitPrice":"3.75","CustomerID":12357.0}
{"InvoiceNo":574740,"StockCode":"23355","Quantity":24,"UnitPrice":"4.15","CustomerID":12357.0}
{"InvoiceNo":574740,"StockCode":"23358","Quantity":24,"UnitPrice":"3.75","CustomerID":12357.0}
{"InvoiceNo":574740,"StockCode":"84030E","Quantity":24,"UnitPrice":"3.75","CustomerID":12357.0}
{"InvoiceNo":574740,"StockCode":"23356","Quantity":24,"UnitPrice":"4.95","CustomerID":12357.0}
{"InvoiceNo":574740,"StockCode":"84029E","Quantity":24,"UnitPrice":"3.75","CustomerID":12357.0}
{"InvoiceNo":574740,"StockCode":"72780","Quantity":12,"UnitPrice":"0.85","CustomerID":12357.0}
{"InvoiceNo":574740,"StockCode":"72783","Quantity":12,"UnitPrice":"2.1","CustomerID":12357.0}
{"InvoiceNo":574740,"StockCode":"37495","Quantity":36,"UnitPrice":"2.95","CustomerID":12357.0}
{"InvoiceNo":574740,"StockCode":"85038","Quantity":72,"UnitPrice":"1.85","CustomerID":12357.0}
{"InvoiceNo":574740,"StockCode":"85040A","Quantity":48,"UnitPrice":"1.45","CustomerID":12357.0}
{"InvoiceNo":574740,"StockCode":"20931","Quantity":12,"UnitPrice":"2.95","CustomerID":12357.0}
{"InvoiceNo":574740,"StockCode":"20932","Quantity":12,"UnitPrice":"2.95","CustomerID":12357.0}
{"InvoiceNo":574740,"StockCode":"22969","Quantity":96,"UnitPrice":"1.25","CustomerID":12357.0}
{"InvoiceNo":574740,"StockCode":"72741","Quantity":72,"UnitPrice":"1.25","CustomerID":12357.0}
{"InvoiceNo":574740,"StockCode":"85174","Quantity":16,"UnitPrice":"4.25","CustomerID":12357.0}
{"InvoiceNo":574740,"StockCode":"21506","Quantity":24,"UnitPrice":"0.42","CustomerID":12357.0}
{"InvoiceNo":574740,"StockCode":"22025","Quantity":24,"UnitPrice":"0.42","CustomerID":12357.0}
{"InvoiceNo":574740,"StockCode":"21507","Quantity":24,"UnitPrice":"0.42","CustomerID":12357.0}
{"InvoiceNo":574740,"StockCode":"22023","Quantity":24,"UnitPrice":"0.42","CustomerID":12357.0}
{"InvoiceNo":574740,"StockCode":"22026","Quantity":24,"UnitPrice":"0.42","CustomerID":12357.0}
{"InvoiceNo":574740,"StockCode":"21508","Quantity":24,"UnitPrice":"0.42","CustomerID":12357.0}
{"InvoiceNo":574740,"StockCode":"22024","Quantity":24,"UnitPrice":"0.42","CustomerID":12357.0}
{"InvoiceNo":574740,"StockCode":"22027","Quantity":24,"UnitPrice":"0.42","CustomerID":12357.0}
{"InvoiceNo":574740,"StockCode":"22028","Quantity":24,"UnitPrice":"0.42","CustomerID":12357.0}
{"InvoiceNo":574740,"StockCode":"22716","Quantity":24,"UnitPrice":"0.42","CustomerID":12357.0}
{"InvoiceNo":574740,"StockCode":"22029","Quantity":24,"UnitPrice":"0.42","CustomerID":12357.0}
{"InvoiceNo":574740,"StockCode":"22712","Quantity":24,"UnitPrice":"0.42","CustomerID":12357.0}
{"InvoiceNo":574740,"StockCode":"22717","Quantity":24,"UnitPrice":"0.42","CustomerID":12357.0}
{"InvoiceNo":574740,"StockCode":"22714","Quantity":24,"UnitPrice":"0.42","CustomerID":12357.0}
{"InvoiceNo":574740,"StockCode":"22718","Quantity":24,"UnitPrice":"0.42","CustomerID":12357.0}
{"InvoiceNo":574740,"StockCode":"22814","Quantity":24,"UnitPrice":"0.42","CustomerID":12357.0}
{"InvoiceNo":574740,"StockCode":"22819","Quantity":24,"UnitPrice":"0.42","CustomerID":12357.0}
{"InvoiceNo":574740,"StockCode":"22983","Quantity":24,"UnitPrice":"0.42","CustomerID":12357.0}
{"InvoiceNo":574740,"StockCode":"22817","Quantity":24,"UnitPrice":"0.42","CustomerID":12357.0}
{"InvoiceNo":574740,"StockCode":"22984","Quantity":24,"UnitPrice":"0.42","CustomerID":12357.0}
{"InvoiceNo":574740,"StockCode":"22815","Quantity":24,"UnitPrice":"0.42","CustomerID":12357.0}
{"InvoiceNo":574740,"StockCode":"22947","Quantity":12,"UnitPrice":"7.95","CustomerID":12357.0}
{"InvoiceNo":574740,"StockCode":"72817","Quantity":24,"UnitPrice":"0.79","CustomerID":12357.0}
{"InvoiceNo":574740,"StockCode":"35598B","Quantity":24,"UnitPrice":"0.65","CustomerID":12357.0}
{"InvoiceNo":574740,"StockCode":"35599B","Quantity":12,"UnitPrice":"1.95","CustomerID":12357.0}
{"InvoiceNo":574740,"StockCode":"35598D","Quantity":24,"UnitPrice":"0.65","CustomerID":12357.0}
{"InvoiceNo":574740,"StockCode":"35599D","Quantity":24,"UnitPrice":"1.95","CustomerID":12357.0}
{"InvoiceNo":574740,"StockCode":"22306","Quantity":12,"UnitPrice":"1.06","CustomerID":12357.0}
{"InvoiceNo":574740,"StockCode":"23267","Quantity":24,"UnitPrice":"1.25","CustomerID":12357.0}
{"InvoiceNo":574740,"StockCode":"23382","Quantity":36,"UnitPrice":"3.29","CustomerID":12357.0}
{"InvoiceNo":574740,"StockCode":"71403","Quantity":12,"UnitPrice":"2.95","CustomerID":12357.0}
{"InvoiceNo":574740,"StockCode":"23494","Quantity":12,"UnitPrice":"5.95","CustomerID":12357.0}
{"InvoiceNo":574740,"StockCode":"23493","Quantity":20,"UnitPrice":"1.95","CustomerID":12357.0}
{"InvoiceNo":574740,"StockCode":"84819","Quantity":8,"UnitPrice":"3.39","CustomerID":12357.0}
{"InvoiceNo":574740,"StockCode":"22511","Quantity":12,"UnitPrice":"3.75","CustomerID":12357.0}
{"InvoiceNo":574740,"StockCode":"21116","Quantity":16,"UnitPrice":"4.25","CustomerID":12357.0}
{"InvoiceNo":574740,"StockCode":"22510","Quantity":12,"UnitPrice":"3.75","CustomerID":12357.0}
{"InvoiceNo":574740,"StockCode":"21411","Quantity":12,"UnitPrice":"4.25","CustomerID":12357.0}
{"InvoiceNo":574740,"StockCode":"22508","Quantity":12,"UnitPrice":"3.75","CustomerID":12357.0}
{"InvoiceNo":574740,"StockCode":"22728","Quantity":8,"UnitPrice":"3.75","CustomerID":12357.0}
{"InvoiceNo":574740,"StockCode":"22726","Quantity":8,"UnitPrice":"3.75","CustomerID":12357.0}
{"InvoiceNo":574740,"StockCode":"22727","Quantity":8,"UnitPrice":"3.75","CustomerID":12357.0}
{"InvoiceNo":574740,"StockCode":"22191","Quantity":6,"UnitPrice":"8.5","CustomerID":12357.0}
{"InvoiceNo":574740,"StockCode":"23178","Quantity":6,"UnitPrice":"2.89","CustomerID":12357.0}
{"InvoiceNo":574740,"StockCode":"23181","Quantity":16,"UnitPrice":"7.5","CustomerID":12357.0}
{"InvoiceNo":574740,"StockCode":"23179","Quantity":6,"UnitPrice":"2.89","CustomerID":12357.0}
{"InvoiceNo":574740,"StockCode":"22193","Quantity":6,"UnitPrice":"8.5","CustomerID":12357.0}
{"InvoiceNo":574740,"StockCode":"23315","Quantity":6,"UnitPrice":"9.95","CustomerID":12357.0}
{"InvoiceNo":574740,"StockCode":"23316","Quantity":6,"UnitPrice":"9.95","CustomerID":12357.0}
{"InvoiceNo":574740,"StockCode":"23317","Quantity":6,"UnitPrice":"9.95","CustomerID":12357.0}
{"InvoiceNo":574740,"StockCode":"23485","Quantity":1,"UnitPrice":"25.0","CustomerID":12357.0}
{"InvoiceNo":574740,"StockCode":"23341","Quantity":6,"UnitPrice":"8.5","CustomerID":12357.0}
{"InvoiceNo":574740,"StockCode":"22966","Quantity":24,"UnitPrice":"1.25","CustomerID":12357.0}
{"InvoiceNo":574740,"StockCode":"84378","Quantity":12,"UnitPrice":"1.45","CustomerID":12357.0}
{"InvoiceNo":574740,"StockCode":"22964","Quantity":12,"UnitPrice":"2.1","CustomerID":12357.0}
{"InvoiceNo":574740,"StockCode":"21154","Quantity":30,"UnitPrice":"1.25","CustomerID":12357.0}
{"InvoiceNo":574740,"StockCode":"47559B","Quantity":30,"UnitPrice":"1.25","CustomerID":12357.0}
{"InvoiceNo":574740,"StockCode":"22897","Quantity":30,"UnitPrice":"1.45","CustomerID":12357.0}
{"InvoiceNo":574740,"StockCode":"21218","Quantity":12,"UnitPrice":"3.75","CustomerID":12357.0}
{"InvoiceNo":574740,"StockCode":"22357","Quantity":12,"UnitPrice":"3.75","CustomerID":12357.0}
{"InvoiceNo":574740,"StockCode":"23247","Quantity":12,"UnitPrice":"2.89","CustomerID":12357.0}
{"InvoiceNo":574740,"StockCode":"22358","Quantity":12,"UnitPrice":"2.95","CustomerID":12357.0}
{"InvoiceNo":574740,"StockCode":"85159A","Quantity":12,"UnitPrice":"1.95","CustomerID":12357.0}
{"InvoiceNo":574740,"StockCode":"85159B","Quantity":12,"UnitPrice":"1.95","CustomerID":12357.0}
{"InvoiceNo":574740,"StockCode":"21216","Quantity":8,"UnitPrice":"4.95","CustomerID":12357.0}
{"InvoiceNo":574740,"StockCode":"23168","Quantity":12,"UnitPrice":"1.25","CustomerID":12357.0}
{"InvoiceNo":574740,"StockCode":"22846","Quantity":4,"UnitPrice":"14.95","CustomerID":12357.0}
{"InvoiceNo":574740,"StockCode":"22847","Quantity":4,"UnitPrice":"14.95","CustomerID":12357.0}
{"InvoiceNo":574740,"StockCode":"23197","Quantity":48,"UnitPrice":"1.25","CustomerID":12357.0}
{"InvoiceNo":574740,"StockCode":"23198","Quantity":48,"UnitPrice":"1.25","CustomerID":12357.0}
{"InvoiceNo":574740,"StockCode":"23196","Quantity":48,"UnitPrice":"1.25","CustomerID":12357.0}
{"InvoiceNo":574740,"StockCode":"22348","Quantity":48,"UnitPrice":"0.85","CustomerID":12357.0}
{"InvoiceNo":574740,"StockCode":"23184","Quantity":36,"UnitPrice":"4.15","CustomerID":12357.0}
{"InvoiceNo":574740,"StockCode":"23302","Quantity":12,"UnitPrice":"1.65","CustomerID":12357.0}
{"InvoiceNo":574740,"StockCode":"21231","Quantity":12,"UnitPrice":"1.25","CustomerID":12357.0}
